relais/__init__.py
relais/base.py
relais/errors.py
relais/index.py
relais/processors.py
relais/py.typed
relais/stream.py
relais/tasks.py
relais/steps/__init__.py
relais/steps/async_iterator_step.py
relais/steps/batch_step.py
relais/steps/distinct_step.py
relais/steps/filter_step.py
relais/steps/flat_map_step.py
relais/steps/group_by_step.py
relais/steps/map_step.py
relais/steps/reduce_step.py
relais/steps/skip_step.py
relais/steps/sort_step.py
relais/steps/take_step.py
relais-0.2.1.dist-info/METADATA
relais-0.2.1.dist-info/WHEEL
relais-0.2.1.dist-info/licenses/LICENSE
relais-0.2.1.dist-info/RECORD
