Metadata-Version: 2.4
Name: relais
Version: 0.2.1
Summary: A practical tool for managing async pipelines.
Project-URL: Homepage, https://github.com/Giskard-AI/relais
Project-URL: Repository, https://github.com/Giskard-AI/relais
Project-URL: Issues, https://github.com/Giskard-AI/relais/issues
Project-URL: Changelog, https://github.com/Giskard-AI/relais/blob/main/CHANGELOG.md
Author-email: Matteo <me@mattbit.com>, Kevin Messiaen <kevind.messiaen@gmail.com>
License: Copyright © 2025 mattbit
License-File: LICENSE
Keywords: async,asyncio,concurrency,data-processing,functional,pipeline,streaming
Classifier: Development Status :: 4 - Beta
Classifier: Intended Audience :: Developers
Classifier: License :: OSI Approved :: MIT License
Classifier: Programming Language :: Python :: 3
Classifier: Programming Language :: Python :: 3.11
Classifier: Programming Language :: Python :: 3.12
Classifier: Programming Language :: Python :: 3.13
Classifier: Topic :: Software Development :: Libraries :: Python Modules
Classifier: Topic :: System :: Distributed Computing
Classifier: Typing :: Typed
Requires-Python: >=3.11
Provides-Extra: dev
Requires-Dist: basedpyright~=1.31.0; extra == 'dev'
Requires-Dist: detect-secrets~=1.5.0; extra == 'dev'
Requires-Dist: ipykernel~=6.30.0; extra == 'dev'
Requires-Dist: pip-audit~=2.9.0; extra == 'dev'
Requires-Dist: pre-commit~=4.2.0; extra == 'dev'
Requires-Dist: pytest-asyncio~=1.1.0; extra == 'dev'
Requires-Dist: pytest~=8.4.1; extra == 'dev'
Requires-Dist: ruff~=0.12.5; extra == 'dev'
Requires-Dist: vermin~=1.6.0; extra == 'dev'
